django_choices_field/__init__.py
django_choices_field/fields.py
django_choices_field/fields.pyi
django_choices_field/py.typed
django_choices_field/types.py
django_choices_field-4.0.0.dist-info/METADATA
django_choices_field-4.0.0.dist-info/WHEEL
django_choices_field-4.0.0.dist-info/licenses/LICENSE
django_choices_field-4.0.0.dist-info/RECORD
